multi_dimensional_clustering/__init__.py
multi_dimensional_clustering/multi_D_clustering.py
multi_dimensional_clustering-0.2.1.dist-info/LICENSE
multi_dimensional_clustering-0.2.1.dist-info/METADATA
multi_dimensional_clustering-0.2.1.dist-info/WHEEL
multi_dimensional_clustering-0.2.1.dist-info/top_level.txt
multi_dimensional_clustering-0.2.1.dist-info/RECORD
