Metadata-Version: 2.1
Name: multi-dimensional-clustering
Version: 0.2.1
Summary: Multi-dimensional clustering visualization tool.
Home-page: https://github.com/PieterMey/multi_dimensional_clustering
Author: Pieter Meyer
Author-email: you@email.com
License: Apache License 2.0
Platform: UNKNOWN
Requires-Dist: numpy
Requires-Dist: matplotlib
Requires-Dist: plotly
Requires-Dist: scikit-learn
Requires-Dist: seaborn
